pyhuffman/__init__.py
pyhuffman/backends/__init__.py
pyhuffman/backends/cffi/__init__.py
pyhuffman/backends/cffi/_hfm.pypy39-pp73-darwin.so
pyhuffman/backends/cffi/build.py
pyhuffman/backends/cython/__init__.py
pyhuffman/backends/cython/_hfm.cpp
pyhuffman/backends/cython/_hfm.pypy39-pp73-darwin.so
pyhuffman/backends/cython/_hfm.pyx
pyhuffman/backends/cython/huffman.pxd
python_huffman-0.1.3.dist-info/METADATA
python_huffman-0.1.3.dist-info/WHEEL
python_huffman-0.1.3.dist-info/top_level.txt
python_huffman-0.1.3.dist-info/RECORD
